ethcx/__init__.py
ethcx/exceptions.py
ethcx/lock.py
ethcx/utils.py
ethcx/compilers/__init__.py
ethcx/compilers/solidity/__init__.py
ethcx/compilers/solidity/install.py
ethcx/compilers/solidity/main.py
ethcx/compilers/solidity/wrapper.py
ethcx/compilers/vyper/__init__.py
ethcx/compilers/vyper/install.py
ethcx/compilers/vyper/main.py
ethcx/compilers/vyper/wrapper.py
ethcx-0.0.4.dist-info/LICENSE
ethcx-0.0.4.dist-info/METADATA
ethcx-0.0.4.dist-info/WHEEL
ethcx-0.0.4.dist-info/top_level.txt
ethcx-0.0.4.dist-info/RECORD
