Metadata-Version: 2.1
Name: ethcx
Version: 0.0.4
Summary: Python wrapper and version management tool for ethereum-targeting compilers.
Home-page: https://github.com/ethpwn/ethcx
Author: Lukas Dresel (forked from py-solc-x by Ben Hause)
Author-email: Lukas-Dresel@users.noreply.github.com
License: MIT
Keywords: ethereum solidity solc vyper
Classifier: Intended Audience :: Developers
Classifier: License :: OSI Approved :: MIT License
Classifier: Natural Language :: English
Classifier: Programming Language :: Python :: 3
Classifier: Programming Language :: Python :: 3.6
Classifier: Programming Language :: Python :: 3.7
Classifier: Programming Language :: Python :: 3.8
Classifier: Programming Language :: Python :: 3.9
Requires-Python: >=3.6, <4
License-File: LICENSE
Requires-Dist: requests (<3,>=2.19.0)
Requires-Dist: semantic-version (<3,>=2.8.1)
Requires-Dist: virtualenv
